typechatpy/__init__.py
typechatpy/translator.py
typechatpy/validator.py
typechatpy-0.4.0.dist-info/LICENSE
typechatpy-0.4.0.dist-info/METADATA
typechatpy-0.4.0.dist-info/WHEEL
typechatpy-0.4.0.dist-info/RECORD
