Metadata-Version: 2.3
Name: typechatpy
Version: 0.4.0
Summary: 
Author: FFengIll
Author-email: fengyouzheng@gmail.com
Requires-Python: >=3.8,<4.0
Classifier: Programming Language :: Python :: 3
Classifier: Programming Language :: Python :: 3.8
Classifier: Programming Language :: Python :: 3.9
Classifier: Programming Language :: Python :: 3.10
Classifier: Programming Language :: Python :: 3.11
Classifier: Programming Language :: Python :: 3.12
Classifier: Programming Language :: Python :: 3.13
Requires-Dist: loguru (>=0.7.3,<0.8.0)
Requires-Dist: pydantic (>=2.1.1,<3.0.0)
